pyrosbag/__init__.py
pyrosbag/pyrosbag.py
pyrosbag-0.1.3.dist-info/DESCRIPTION.rst
pyrosbag-0.1.3.dist-info/METADATA
pyrosbag-0.1.3.dist-info/RECORD
pyrosbag-0.1.3.dist-info/WHEEL
pyrosbag-0.1.3.dist-info/metadata.json
pyrosbag-0.1.3.dist-info/top_level.txt
