Metadata-Version: 1.1
Name: pyrosbag
Version: 0.1.3
Summary: Programmatically control ROS Bag files with Python
Home-page: https://github.com/masasin/pyrosbag
Author: Jean Nassar
Author-email: jeannassar5@gmail.com
License: MIT license
Download-URL: https://github.com/masasin/pyrosbag/tarball/0.1.0
Keywords: pyrosbag,ros,bag
Platform: UNKNOWN
Classifier: Development Status :: 2 - Pre-Alpha
Classifier: Intended Audience :: Developers
Classifier: License :: OSI Approved :: MIT License
Classifier: Natural Language :: English
Classifier: Programming Language :: Python :: 2
Classifier: Programming Language :: Python :: 2.7
Classifier: Programming Language :: Python :: 3
Classifier: Programming Language :: Python :: 3.4
Classifier: Programming Language :: Python :: 3.5
Classifier: Programming Language :: Python :: 3.6
